oam_sso/__init__.py
oam_sso-0.0.1.dist-info/METADATA
oam_sso-0.0.1.dist-info/WHEEL
oam_sso-0.0.1.dist-info/top_level.txt
oam_sso-0.0.1.dist-info/RECORD
